{
  "$schema": "https://json-schema.org/draft/2020-12/schema",
  "$id": "https://dreative.local/schemas/verify.schema.json",
  "title": "Dreative Verification Report",
  "type": "object",
  "additionalProperties": false,
  "required": ["version", "generatedAt", "evidence"],
  "properties": {
    "version": { "const": 1 },
    "generatedAt": { "type": "string", "format": "date-time" },
    "evidence": {
      "type": "array",
      "items": {
        "type": "object",
        "additionalProperties": false,
        "required": ["id", "criterion", "status", "evidence", "proof"],
        "properties": {
          "id": { "type": "string", "minLength": 1 },
          "criterion": { "type": "string", "minLength": 1 },
          "status": { "enum": ["pass", "fail", "not-applicable"] },
          "evidence": { "type": "string", "minLength": 1 },
          "proof": {
            "type": "object",
            "additionalProperties": false,
            "required": ["timestamp"],
            "properties": {
              "timestamp": { "type": "string", "format": "date-time" },
              "artifactPath": { "type": "string", "minLength": 1 },
              "viewport": {
                "type": "object",
                "additionalProperties": false,
                "required": ["width", "height"],
                "properties": {
                  "width": { "type": "number", "exclusiveMinimum": 0 },
                  "height": { "type": "number", "exclusiveMinimum": 0 },
                  "dpr": { "type": "number", "exclusiveMinimum": 0 }
                }
              },
              "command": { "type": "string", "minLength": 1 },
              "exitCode": { "type": "integer" },
              "consoleErrorCount": { "type": "integer", "minimum": 0 },
              "testedUrl": { "type": "string", "minLength": 1 },
              "averageFps": { "type": "number", "exclusiveMinimum": 0 },
              "maxFrameTimeMs": { "type": "number", "minimum": 0 },
              "playwrightTestId": { "type": "string", "minLength": 1 }
            },
            "anyOf": [
              { "required": ["artifactPath"] },
              { "required": ["command", "exitCode"] },
              { "required": ["consoleErrorCount"] },
              { "required": ["testedUrl"] },
              { "required": ["averageFps"] },
              { "required": ["maxFrameTimeMs"] },
              { "required": ["playwrightTestId"] }
            ]
          }
        }
      }
    }
  }
}
